omni_fs_mcp/__init__.py
omni_fs_mcp/backend_manager.py
omni_fs_mcp/dal.py
omni_fs_mcp/mcp_server.py
omni_fs_mcp-0.1.8.dist-info/METADATA
omni_fs_mcp-0.1.8.dist-info/WHEEL
omni_fs_mcp-0.1.8.dist-info/entry_points.txt
omni_fs_mcp-0.1.8.dist-info/licenses/LICENSE
omni_fs_mcp-0.1.8.dist-info/RECORD
