Metadata-Version: 2.4
Name: omni-fs-mcp
Version: 0.1.8
Summary: Omni-FS-MCP is an MCP server that supports managing multiple types of file systems, such as local FS, S3, R2, B2, WebDAV, and others, in one MCP server. It is built on top of OpenDAL.
Project-URL: Homepage, https://github.com/vaayne/omni-fs-mcp
Project-URL: Repository, https://github.com/vaayne/omni-fs-mcp
Project-URL: Issues, https://github.com/vaayne/omni-fs-mcp/issues
Author-email: Vaayne <liu.vaayne@gmail.com>
License: MIT
License-File: LICENSE
Keywords: filesystem,mcp,opendal,s3,webdav
Classifier: Development Status :: 4 - Beta
Classifier: Intended Audience :: Developers
Classifier: License :: OSI Approved :: MIT License
Classifier: Operating System :: OS Independent
Classifier: Programming Language :: Python :: 3
Classifier: Programming Language :: Python :: 3.11
Classifier: Programming Language :: Python :: 3.12
Classifier: Programming Language :: Python :: 3.13
Classifier: Topic :: Software Development :: Libraries :: Python Modules
Classifier: Topic :: System :: Filesystems
Requires-Python: >=3.11
Requires-Dist: mcp>=1.11.0
Requires-Dist: opendal>=0.45.20
Requires-Dist: uvicorn>=0.35.0
